pls_cli/__init__.py
pls_cli/please.py
pls_cli/utils/__init__.py
pls_cli/utils/quotes.json
pls_cli/utils/quotes.py
pls_cli/utils/settings.py
pls_cli-0.3.4.dist-info/LICENSE
pls_cli-0.3.4.dist-info/METADATA
pls_cli-0.3.4.dist-info/WHEEL
pls_cli-0.3.4.dist-info/entry_points.txt
pls_cli-0.3.4.dist-info/RECORD
