Metadata-Version: 2.1
Name: pls-cli
Version: 0.3.4
Summary: Minimalist and full configurable greetings and TODO list
Home-page: https://guedesfelipe.github.io/pls-cli/
Keywords: pls,please,todo,cli
Author: Felipe Guedes
Author-email: contatofelipeguedes@gmail.com
Requires-Python: >=3.7,<4.0
Classifier: Programming Language :: Python :: 3
Classifier: Programming Language :: Python :: 3.7
Classifier: Programming Language :: Python :: 3.8
Classifier: Programming Language :: Python :: 3.9
Classifier: Programming Language :: Python :: 3.10
Classifier: Programming Language :: Python :: 3.11
Classifier: Programming Language :: Python :: 3.12
Requires-Dist: rich (>=13.7.0,<14.0.0)
Requires-Dist: typer[all] (>=0.9.0,<0.10.0)
Project-URL: Documentation, https://guedesfelipe.github.io/pls-cli/
Project-URL: Repository, https://github.com/guedesfelipe/pls-cli
